compare_datasets/__init__.py
compare_datasets/analyse_deviations.py
compare_datasets/boolean_comparison.py
compare_datasets/datetime_comparison.py
compare_datasets/html_report.py
compare_datasets/jaccard_similarity.py
compare_datasets/metadata.py
compare_datasets/numeric_comparisons.py
compare_datasets/prepare.py
compare_datasets/resources/report_template.html
compare_datasets/string_comparisons.py
compare_datasets/structure.py
compare_datasets/tests/62E99100
compare_datasets/tests/archive.py
compare_datasets/tests/cases.md
compare_datasets/tests/report_20231127221708.html
compare_datasets/utilities.py
compare_datasets-0.1.21.dist-info/LICENSE.txt
compare_datasets-0.1.21.dist-info/METADATA
compare_datasets-0.1.21.dist-info/WHEEL
compare_datasets-0.1.21.dist-info/RECORD
