Metadata-Version: 2.1
Name: compare_datasets
Version: 0.1.21
Summary: The library that compares two dataframes
License: MIT
Author: Kumar Shantanu
Requires-Python: >=3.8,<=3.12
Classifier: License :: OSI Approved :: MIT License
Classifier: Programming Language :: Python :: 3
Classifier: Programming Language :: Python :: 3.8
Classifier: Programming Language :: Python :: 3.9
Classifier: Programming Language :: Python :: 3.10
Classifier: Programming Language :: Python :: 3.11
Requires-Dist: Levenshtein (>=0.23.0,<0.24.0)
Requires-Dist: jinja2 (>=3.1.2,<4.0.0)
Requires-Dist: pandas (>1.0.0)
Requires-Dist: polars (>=0.19.5)
Requires-Dist: scipy (>=1.10.0,<2.0.0)
Requires-Dist: tabulate (>=0.8.9,<0.9.0)
Requires-Dist: tqdm (>=4.66.1,<5.0.0)
